gpsea/__init__.py
gpsea/config.py
gpsea/io.py
gpsea/py.typed
gpsea/util.py
gpsea/analysis/__init__.py
gpsea/analysis/_base.py
gpsea/analysis/_partition.py
gpsea/analysis/_util.py
gpsea/analysis/clf/__init__.py
gpsea/analysis/clf/_api.py
gpsea/analysis/clf/_counter.py
gpsea/analysis/clf/_gt_classifiers.py
gpsea/analysis/clf/_pheno.py
gpsea/analysis/clf/_test__gt_classifiers.py
gpsea/analysis/clf/_util.py
gpsea/analysis/mtc_filter/__init__.py
gpsea/analysis/mtc_filter/_impl.py
gpsea/analysis/pcats/__init__.py
gpsea/analysis/pcats/_config.py
gpsea/analysis/pcats/_impl.py
gpsea/analysis/pcats/stats/__init__.py
gpsea/analysis/pcats/stats/_stats.py
gpsea/analysis/pcats/stats/_test__stats.py
gpsea/analysis/predicate/__init__.py
gpsea/analysis/predicate/_api.py
gpsea/analysis/predicate/_predicates.py
gpsea/analysis/predicate/_variant.py
gpsea/analysis/pscore/__init__.py
gpsea/analysis/pscore/_api.py
gpsea/analysis/pscore/_hpo.py
gpsea/analysis/pscore/_measurement.py
gpsea/analysis/pscore/stats/__init__.py
gpsea/analysis/pscore/stats/_stats.py
gpsea/analysis/temporal/__init__.py
gpsea/analysis/temporal/_api.py
gpsea/analysis/temporal/_base.py
gpsea/analysis/temporal/_util.py
gpsea/analysis/temporal/endpoint/__init__.py
gpsea/analysis/temporal/endpoint/_impl.py
gpsea/analysis/temporal/stats/__init__.py
gpsea/analysis/temporal/stats/_api.py
gpsea/analysis/temporal/stats/_impl.py
gpsea/model/__init__.py
gpsea/model/_base.py
gpsea/model/_cohort.py
gpsea/model/_gt.py
gpsea/model/_phenotype.py
gpsea/model/_protein.py
gpsea/model/_temporal.py
gpsea/model/_test_gt.py
gpsea/model/_test_temporal.py
gpsea/model/_test_tx.py
gpsea/model/_tx.py
gpsea/model/_variant.py
gpsea/model/_variant_effects.py
gpsea/model/genome/GCF_000001405.25_GRCh37.p13_assembly_report.tsv
gpsea/model/genome/GCF_000001405.39_GRCh38.p13_assembly_report.tsv
gpsea/model/genome/__init__.py
gpsea/model/genome/_builds.py
gpsea/model/genome/_genome.py
gpsea/model/genome/_test_builds.py
gpsea-0.9.13.dist-info/licenses/LICENSE
gpsea-0.9.13.dist-info/METADATA
gpsea-0.9.13.dist-info/WHEEL
gpsea-0.9.13.dist-info/top_level.txt
gpsea-0.9.13.dist-info/RECORD
