Metadata-Version: 2.4
Name: gpsea
Version: 0.9.13
Summary: Discover genotype-phenotype correlations with GA4GH phenopackets
Author-email: Lauren Rekerle <lauren.rekerle@jax.org>, Daniel Danis <daniel.danis@bih-charite.de>, Peter Robinson <peter.robinson@bih-charite.de>
License: MIT License
Project-URL: homepage, https://github.com/P2GX/gpsea
Project-URL: repository, https://github.com/P2GX/gpsea.git
Project-URL: documentation, https://P2GX.github.io/gpsea/stable
Project-URL: bugtracker, https://github.com/P2GX/gpsea/issues
Keywords: Global Alliance for Genomics and Health,GA4GH Phenopacket Schema,Human Phenotype Ontology,GA4GH,Genotype-phenotype correlation,HPO
Classifier: License :: OSI Approved :: MIT License
Classifier: Operating System :: OS Independent
Classifier: Development Status :: 3 - Alpha
Classifier: Programming Language :: Python :: 3.10
Classifier: Programming Language :: Python :: 3.11
Classifier: Programming Language :: Python :: 3.12
Classifier: Intended Audience :: Science/Research
Classifier: Topic :: Scientific/Engineering :: Bio-Informatics
Requires-Python: >=3.10
License-File: LICENSE
Requires-Dist: hpo-toolkit>=0.3.0
Requires-Dist: stairval>=0.2.1
Requires-Dist: Jinja2<4.0.0,>=3.1.4
Requires-Dist: phenopackets>=2.0.2.post4
Requires-Dist: pandas<3.0.0,>=2.0.0
Requires-Dist: requests<3.0,>=2.25.0
Requires-Dist: scipy<2.0,>=1.10
Requires-Dist: statsmodels>=0.13.0
Requires-Dist: numpy>=1.23
Requires-Dist: matplotlib<4.0,>=3.2.0
Requires-Dist: ratelimit<3,>=2.2.1
Requires-Dist: tqdm>=4.60
Provides-Extra: test
Requires-Dist: phenopacket-store-toolkit>=0.1.2; extra == "test"
Requires-Dist: pytest<8.0.0,>=7.0.0; extra == "test"
Requires-Dist: ruff==0.12.1; extra == "test"
Provides-Extra: docs
Requires-Dist: sphinx>=7.0.0; extra == "docs"
Requires-Dist: sphinx-rtd-theme>=1.3.0; extra == "docs"
Requires-Dist: sphinx-rtd-dark-mode>=1.3.0; extra == "docs"
Requires-Dist: sphinx-copybutton>=0.5.0; extra == "docs"
Dynamic: license-file
